rijksplotlib/__init__.py
rijksplotlib/color.py
rijksplotlib/colormaps.py
rijksplotlib/pylint_rules.py
rijksplotlib/pyplot.py
rijksplotlib/utils.py
rijksplotlib/validate.py
rijksplotlib/stylesheets/__init__.py
rijksplotlib/stylesheets/rws_report.mplstyle
rijksplotlib-1.0.5.dist-info/LICENSE
rijksplotlib-1.0.5.dist-info/METADATA
rijksplotlib-1.0.5.dist-info/WHEEL
rijksplotlib-1.0.5.dist-info/top_level.txt
rijksplotlib-1.0.5.dist-info/RECORD
