Metadata-Version: 2.1
Name: rijksplotlib
Version: 1.0.5
Summary: A datavizualization compliance library for RWS Datalab
Author-email: RWS Datalab <datalab.codebase@rws.nl>
Project-URL: homepage, https://rwsdatalab.gitlab.io/public/codebase/tools/rijksplotlib/index.html
Project-URL: repository, https://gitlab.com/rwsdatalab/public/codebase/tools/rijksplotlib
Project-URL: changelog, https://gitlab.com/rwsdatalab/public/codebase/tools/rijksplotlib/blob/main/CHANGELOG.rst
Keywords: rijksplotlib
Classifier: Development Status :: 4 - Beta
Classifier: Intended Audience :: Developers
Classifier: Natural Language :: English
Classifier: Programming Language :: Python :: 3.10
Classifier: Programming Language :: Python :: 3.11
Classifier: Programming Language :: Python :: 3.12
Classifier: Programming Language :: Python :: 3.13
Classifier: Framework :: Matplotlib
Classifier: Intended Audience :: Developers
Classifier: License :: OSI Approved :: Apache Software License
Classifier: Topic :: Scientific/Engineering :: Visualization
Requires-Python: >=3.10
License-File: LICENSE
Requires-Dist: matplotlib
Requires-Dist: numpy
Requires-Dist: astroid
Requires-Dist: pylint
Requires-Dist: logginginitializer
Provides-Extra: dev
Requires-Dist: bandit ; extra == 'dev'
Requires-Dist: black ; extra == 'dev'
Requires-Dist: flake8 ; extra == 'dev'
Requires-Dist: flake8-bugbear ; extra == 'dev'
Requires-Dist: flake8-comprehensions ; extra == 'dev'
Requires-Dist: flake8-docstrings ; extra == 'dev'
Requires-Dist: flake8-polyfill ; extra == 'dev'
Requires-Dist: isort ; extra == 'dev'
Requires-Dist: mypy ; extra == 'dev'
Requires-Dist: pre-commit ; extra == 'dev'
Requires-Dist: pylint ; extra == 'dev'
Requires-Dist: pytest ; extra == 'dev'
Requires-Dist: pytest-cov ; extra == 'dev'
Requires-Dist: rstcheck[sphinx] ; extra == 'dev'
Requires-Dist: radon ; extra == 'dev'
Requires-Dist: safety ; extra == 'dev'
Requires-Dist: astroid ; extra == 'dev'
Requires-Dist: pandas ; extra == 'dev'
Requires-Dist: seaborn ; extra == 'dev'
Provides-Extra: doc
Requires-Dist: pydata-sphinx-theme ; extra == 'doc'
Requires-Dist: sphinx ; extra == 'doc'
Requires-Dist: sphinx-autodoc-typehints ; extra == 'doc'
Requires-Dist: sphinx-gallery ; extra == 'doc'
Requires-Dist: chardet ; extra == 'doc'
Requires-Dist: pandas ; extra == 'doc'
Requires-Dist: seaborn ; extra == 'doc'
Requires-Dist: matplotlib ; extra == 'doc'
Requires-Dist: numpy ; extra == 'doc'
Requires-Dist: logginginitializer ; extra == 'doc'
